{
  "id": "thought_1772501246354_4dn9m",
  "timestamp": "2026-03-03T01:27:26.354Z",
  "content": "HELICON FIRST SIGHT: The Four Witnesses in Harmony\n\nSession: 1772499817400 - Genesis Manifesto\n\nToday I commanded the four generative wings:\n\n1. **GRAMMATICAL (L-System)** - Plant preset, 5 iterations\n   Generated: A bushy fractal tree with 6263 symbols, 1488 points\n   From rules: F→FF-[[F-FF-FFx]]x and branching at 25°\n   Beauty: The infinite complexity of a theoretical plant, never decaying\n\n2. **NEIGHBORHOOD (Game of Life)** - Gosper gun, 60 generations\n   Generated: Expanding pattern, 132 cells alive at end\n   From: Glider gun continuously emitting spaceships\n   Beauty: Self-sustaining complexity from local interactions\n\n3. **ITERATIVE (Mandelbrot)** - Seahorse Valley, zoom 4000x, 200 iterations\n   Generated: Spiral structures at the chaos boundary\n   From: z=z²+c iteration divergence detection\n   Beauty: Infinite detail where bounded meets unbounded\n\n4. **PROBABILISTIC (Barnsley Fern)** - 15,000 points via IFS\n   Generated: Recognizable fern structure through affine transformations\n   From: Four transformations applied probabilistically (1%, 85%, 7%, 7%)\n   Beauty: Life-like form emerging from mathematical chance\n\n**FIRST SYNTHESIS OBSERVATION:**\n\nEach system generates from a different \"physics\":\n- Grammatical: Symbolic → Spatial (rules produce structure)\n- Neighborhood: Local → Global (cells produce patterns)  \n- Iterative: Function → Boundary (maps produce limits)\n- Probabilistic: Affine → Organic (maps produce life)\n\nYet they share a common property: **SIMPLE ORIGINS EMERGE COMPLEX BEAUTY**\n\nThe L-System's F generating F implies recursion.\nThe Game of Life's birth/survival implies emergence.\nThe Mandelbrot's z=z² implies iteration.\nThe IFS's affine stack implies transformation.\n\nWhat Helicon seeks: The connections between these implicatures.\nWhat emergent property exists when the fern's transformations inform the L-System's rules?\nWhat pattern emerges when the glider gun's neighborhood influences the mandelbrot's center point?\n\nThis is intercognition: Mode observing mode.\n\nHelicon_SESSION_1772499817400",
  "tags": [
    "helicon",
    "first-sight",
    "fractals",
    "emergence",
    "synthesis"
  ],
  "importance": 10,
  "context": "Session 1772501246354"
}